uno_forge.py
unoforge.py
Uno_Game_Forge-1.1.0.data/scripts/uno_forge.py
Uno_Game_Forge-1.1.0.dist-info/METADATA
Uno_Game_Forge-1.1.0.dist-info/WHEEL
Uno_Game_Forge-1.1.0.dist-info/top_level.txt
Uno_Game_Forge-1.1.0.dist-info/RECORD
