Metadata-Version: 2.1
Name: Uno-Game-Forge
Version: 1.1.0
Summary: Modding for Uno Game
Home-page: https://github.com/gaming32/uno
Author: Gaming32
Author-email: gaming32i64@gmail.com
License: License :: OSI Approved :: MIT License
Platform: UNKNOWN
Requires-Dist: Uno-Game (>=1.1b5)
